pyshgp/__init__.py
pyshgp/monitoring.py
pyshgp/tap.py
pyshgp/utils.py
pyshgp/validation.py
pyshgp/gp/__init__.py
pyshgp/gp/estimators.py
pyshgp/gp/evaluation.py
pyshgp/gp/genome.py
pyshgp/gp/genome_old.py
pyshgp/gp/individual.py
pyshgp/gp/population.py
pyshgp/gp/search.py
pyshgp/gp/selection.py
pyshgp/gp/variation.py
pyshgp/push/__init__.py
pyshgp/push/atoms.py
pyshgp/push/atoms_old.py
pyshgp/push/config.py
pyshgp/push/instruction.py
pyshgp/push/instruction_set.py
pyshgp/push/interpreter.py
pyshgp/push/program.py
pyshgp/push/stack.py
pyshgp/push/state.py
pyshgp/push/type_library.py
pyshgp/push/types.py
pyshgp/push/instructions/__init__.py
pyshgp/push/instructions/code.py
pyshgp/push/instructions/common.py
pyshgp/push/instructions/io.py
pyshgp/push/instructions/logical.py
pyshgp/push/instructions/numeric.py
pyshgp/push/instructions/text.py
pyshgp/push/instructions/vector.py
pyshgp-0.1.8.dist-info/LICENSE
pyshgp-0.1.8.dist-info/METADATA
pyshgp-0.1.8.dist-info/WHEEL
pyshgp-0.1.8.dist-info/top_level.txt
pyshgp-0.1.8.dist-info/RECORD
