Metadata-Version: 2.1
Name: pyshgp
Version: 0.1.8
Summary: Push Genetic Programming in Python
Home-page: https://github.com/erp12/pyshgp
Author: Eddie Pantridge
Author-email: erp12@hampshire.edu
License: MIT
Keywords: push gp,genetic programming,pushgp,gp,push
Platform: UNKNOWN
Classifier: Development Status :: 4 - Beta
Classifier: Programming Language :: Python :: 3
Classifier: Intended Audience :: Science/Research
Classifier: Intended Audience :: Developers
Classifier: Topic :: Scientific/Engineering :: Artificial Intelligence
Requires-Dist: numpy (>=1.12.0)
Requires-Dist: scipy (>=0.18.0)
Requires-Dist: pandas (>=0.23.4)
Requires-Dist: pyrsistent (>=0.16.0)
